koil/__init__.py
koil/decorators.py
koil/errors.py
koil/helpers.py
koil/koil.py
koil/protocols.py
koil/py.typed
koil/qt.py
koil/types.py
koil/utils.py
koil/vars.py
koil/composition/__init__.py
koil/composition/base.py
koil/contrib/__init__.py
koil/contrib/pytest.py
koil/contrib/pytest_qt.py
koil-2.2.0.dist-info/METADATA
koil-2.2.0.dist-info/WHEEL
koil-2.2.0.dist-info/RECORD
