Metadata-Version: 2.4
Name: koil
Version: 2.2.0
Summary: Async for a sync world
Author-email: jhnnsrs <jhnnsrs@gmail.com>
License-Expression: MIT
Requires-Python: >=3.11
Requires-Dist: janus<2,>=1.0.0
Requires-Dist: pydantic>=2
Provides-Extra: qtpy
Requires-Dist: qtpy>1; extra == 'qtpy'
